allprs/__init__.py
allprs/config.py
allprs/utils.py
allprs-1.2.0.dist-info/WHEEL
allprs-1.2.0.dist-info/entry_points.txt
allprs-1.2.0.dist-info/METADATA
allprs-1.2.0.dist-info/RECORD
