Metadata-Version: 2.4
Name: allprs
Version: 1.2.0
Summary: Approve and merge PRs in bulk
Author: GideonBear
License-Expression: GPL-3.0-only
Classifier: License :: OSI Approved :: GNU General Public License v3 (GPLv3)
Classifier: Programming Language :: Python :: 3 :: Only
Classifier: Programming Language :: Python :: 3.14
Requires-Dist: githubkit>=0.13.6
Requires-Dist: prompt-toolkit>=3.0.52
Requires-Python: >=3.14
Project-URL: bugs, https://github.com/GideonBear/allprs/issues
Project-URL: homepage, https://github.com/GideonBear/allprs
